docktor/Manager.py
docktor/Server.py
docktor/__init__.py
docktor/__main__.py
docktor/data/Dockerfile
docktor/data/start.sh
docktor/data/service/privoxy/config
docktor/data/service/privoxy/run
docktor/data/service/tor/run
docktor/data/service/tor/torrc
docktor-0.42.dist-info/DESCRIPTION.rst
docktor-0.42.dist-info/METADATA
docktor-0.42.dist-info/RECORD
docktor-0.42.dist-info/WHEEL
docktor-0.42.dist-info/entry_points.txt
docktor-0.42.dist-info/metadata.json
docktor-0.42.dist-info/top_level.txt
