Metadata-Version: 2.0
Name: docktor
Version: 0.42
Summary: starts n tor docker containers with an api
Home-page: https://github.com/smthnspcl/docktor
Author: Pascal Eberlein
Author-email: pascal@eberlein.io
License: UNKNOWN
Keywords: docker tor python
Platform: UNKNOWN
Classifier: Development Status :: 3 - Alpha
Classifier: Intended Audience :: Developers
Classifier: Topic :: Software Development :: Build Tools
Classifier: License :: OSI Approved :: MIT License
Classifier: Programming Language :: Python :: 3.7
Requires-Dist: docker
Requires-Dist: loguru
Requires-Dist: psutil
Requires-Dist: sanic
Requires-Dist: stem
